{
  "type": "FeatureCollection",
  "features": [
    {
      "type": "Feature",
      "properties": {
        "id": "tb-buoy-01",
        "name": "Prototype Buoy"
      },
      "geometry": {
        "type": "Point",
        "coordinates": [-82.65, 27.85]
      }
    },
    {
      "type": "Feature",
      "properties": {
        "id": "tb-buoy-02",
        "name": "Backup Buoy"
      },
      "geometry": {
        "type": "Point",
        "coordinates": [-82.70, 27.90]
      }
    }
  ]
}
