{
  "type": "FeatureCollection",
  "features": [
    {
      "type": "Feature",
      "properties": {
        "id": "tb-buoy-01",
        "name": "Prototype Buoy"
      },
      "geometry": {
        "type": "Point",
        "coordinates": [27.759358, -82.635293]
      }
    },
    {
      "type": "Feature",
      "properties": {
        "id": "tb-buoy-02",
        "name": "Backup Buoy"
      },
      "geometry": {
        "type": "Point",
        "coordinates": [27.758653, -82.632095]
      }
    }
  ]
}
